pathenger/__init__.py
pathenger-0.3.0.dist-info/METADATA
pathenger-0.3.0.dist-info/WHEEL
pathenger-0.3.0.dist-info/top_level.txt
pathenger-0.3.0.dist-info/RECORD
