Metadata-Version: 2.2
Name: pathenger
Version: 0.3.0
Summary: A utility package for determining the paths of executable files and temporary directories, especially useful for applications packaged with PyInstaller.
Home-page: https://github.com/p12m3ikm4d/pathenger
Author: p12m3ikm4d
Author-email: issue.no9@gmail.com
Classifier: Programming Language :: Python :: 3
Classifier: Operating System :: OS Independent
Requires-Python: >=3.6
Dynamic: author
Dynamic: author-email
Dynamic: classifier
Dynamic: description
Dynamic: description-content-type
Dynamic: home-page
Dynamic: requires-python
Dynamic: summary
